.editorconfig
.gitignore
.travis.yml
Makefile
README.md
demo.py
setup.py
tox.ini
csboilerplate/__init__.py
csboilerplate/test_module.py
csboilerplate.egg-info/PKG-INFO
csboilerplate.egg-info/SOURCES.txt
csboilerplate.egg-info/dependency_links.txt
csboilerplate.egg-info/requires.txt
csboilerplate.egg-info/top_level.txt
doc/conf.py
doc/index.rst