Metadata-Version: 2.1
Name: csboilerplate
Version: 0.1.0
Summary: console script boilerplate
Home-page: https://github.com/hbschr/csboilerplate
Author: heiko huebscher
Author-email: heiko.huebscher@gmail.com
License: MIT
Keywords: cli console commandline
Platform: UNKNOWN
Classifier: Development Status :: 3 - Alpha
Classifier: Environment :: Console
Classifier: Intended Audience :: Developers
Classifier: Topic :: Software Development :: Libraries :: Python Modules
Classifier: Topic :: Software Development :: Libraries :: Application Frameworks
Classifier: License :: OSI Approved :: MIT License
Classifier: Programming Language :: Python :: 3.6
Provides-Extra: dev
Provides-Extra: doc
